[{
    "GRUPOMERCADO": "SUINOCULTURA",
    "ANOMES": "2020-07",
    "QTDE_VISIT": 104
}, {
    "GRUPOMERCADO": "AQUICULTURA",
    "ANOMES": "2020-10",
    "QTDE_VISIT": 15
}, {
    "GRUPOMERCADO": "AQUICULTURA",
    "ANOMES": "2021-01",
    "QTDE_VISIT": 4
}, {
    "GRUPOMERCADO": "AVICULTURA",
    "ANOMES": "2021-01",
    "QTDE_VISIT": 18
}, {
    "GRUPOMERCADO": "SUINOCULTURA",
    "ANOMES": "2021-05",
    "QTDE_VISIT": 105
}, {
    "GRUPOMERCADO": "AVICULTURA",
    "ANOMES": "2020-01",
    "QTDE_VISIT": 72
}, {
    "GRUPOMERCADO": "ANIMAIS DE COMPANHIA",
    "ANOMES": "2020-02",
    "QTDE_VISIT": 1654
}, {
    "GRUPOMERCADO": "SUINOCULTURA",
    "ANOMES": "2020-02",
    "QTDE_VISIT": 119
}, {
    "GRUPOMERCADO": "ANIMAIS DE COMPANHIA",
    "ANOMES": "2020-03",
    "QTDE_VISIT": 1429
}, {
    "GRUPOMERCADO": "AVICULTURA",
    "ANOMES": "2020-06",
    "QTDE_VISIT": 94
}, {
    "GRUPOMERCADO": "AQUICULTURA",
    "ANOMES": "2020-09",
    "QTDE_VISIT": 16
}, {
    "GRUPOMERCADO": "SUINOCULTURA",
    "ANOMES": "2020-09",
    "QTDE_VISIT": 118
}, {
    "GRUPOMERCADO": "SUINOCULTURA",
    "ANOMES": "2021-02",
    "QTDE_VISIT": 68
}, {
    "GRUPOMERCADO": "ANIMAIS DE COMPANHIA",
    "ANOMES": "2021-06",
    "QTDE_VISIT": 1953
}, {
    "GRUPOMERCADO": "PECUÁRIA",
    "ANOMES": "2020-05",
    "QTDE_VISIT": 3844
}, {
    "GRUPOMERCADO": "AQUICULTURA",
    "ANOMES": "2020-06",
    "QTDE_VISIT": 23
}, {
    "GRUPOMERCADO": "SUINOCULTURA",
    "ANOMES": "2020-06",
    "QTDE_VISIT": 189
}, {
    "GRUPOMERCADO": "PECUÁRIA",
    "ANOMES": "2020-08",
    "QTDE_VISIT": 4959
}, {
    "GRUPOMERCADO": "AVICULTURA",
    "ANOMES": "2020-09",
    "QTDE_VISIT": 102
}, {
    "GRUPOMERCADO": "AVICULTURA",
    "ANOMES": "2020-12",
    "QTDE_VISIT": 40
}, {
    "GRUPOMERCADO": "SUINOCULTURA",
    "ANOMES": "2020-12",
    "QTDE_VISIT": 59
}, {
    "GRUPOMERCADO": "PECUÁRIA",
    "ANOMES": "2021-02",
    "QTDE_VISIT": 2971
}, {
    "GRUPOMERCADO": "AVICULTURA",
    "ANOMES": "2021-03",
    "QTDE_VISIT": 87
}, {
    "GRUPOMERCADO": "ANIMAIS DE COMPANHIA",
    "ANOMES": "2020-01",
    "QTDE_VISIT": 1076
}, {
    "GRUPOMERCADO": "PECUÁRIA",
    "ANOMES": "2020-01",
    "QTDE_VISIT": 1279
}, {
    "GRUPOMERCADO": "SUINOCULTURA",
    "ANOMES": "2020-03",
    "QTDE_VISIT": 106
}, {
    "GRUPOMERCADO": "SUINOCULTURA",
    "ANOMES": "2020-04",
    "QTDE_VISIT": 138
}, {
    "GRUPOMERCADO": "AQUICULTURA",
    "ANOMES": "2020-05",
    "QTDE_VISIT": 28
}, {
    "GRUPOMERCADO": "ANIMAIS DE COMPANHIA",
    "ANOMES": "2020-06",
    "QTDE_VISIT": 2714
}, {
    "GRUPOMERCADO": "PECUÁRIA",
    "ANOMES": "2020-06",
    "QTDE_VISIT": 4487
}, {
    "GRUPOMERCADO": "AQUICULTURA",
    "ANOMES": "2020-08",
    "QTDE_VISIT": 22
}, {
    "GRUPOMERCADO": "AQUICULTURA",
    "ANOMES": "2021-02",
    "QTDE_VISIT": 10
}, {
    "GRUPOMERCADO": "SUINOCULTURA",
    "ANOMES": "2021-04",
    "QTDE_VISIT": 149
}, {
    "GRUPOMERCADO": "SUINOCULTURA",
    "ANOMES": "2020-01",
    "QTDE_VISIT": 81
}, {
    "GRUPOMERCADO": "AQUICULTURA",
    "ANOMES": "2020-04",
    "QTDE_VISIT": 28
}, {
    "GRUPOMERCADO": "SUINOCULTURA",
    "ANOMES": "2020-05",
    "QTDE_VISIT": 207
}, {
    "GRUPOMERCADO": "SUINOCULTURA",
    "ANOMES": "2020-08",
    "QTDE_VISIT": 117
}, {
    "GRUPOMERCADO": "PECUÁRIA",
    "ANOMES": "2020-10",
    "QTDE_VISIT": 4002
}, {
    "GRUPOMERCADO": "ANIMAIS DE COMPANHIA",
    "ANOMES": "2021-01",
    "QTDE_VISIT": 1363
}, {
    "GRUPOMERCADO": "PECUÁRIA",
    "ANOMES": "2021-01",
    "QTDE_VISIT": 2234
}, {
    "GRUPOMERCADO": "AQUICULTURA",
    "ANOMES": "2021-04",
    "QTDE_VISIT": 7
}, {
    "GRUPOMERCADO": "PECUÁRIA",
    "ANOMES": "2020-02",
    "QTDE_VISIT": 2580
}, {
    "GRUPOMERCADO": "PECUÁRIA",
    "ANOMES": "2020-03",
    "QTDE_VISIT": 3724
}, {
    "GRUPOMERCADO": "AVICULTURA",
    "ANOMES": "2020-04",
    "QTDE_VISIT": 45
}, {
    "GRUPOMERCADO": "ANIMAIS DE COMPANHIA",
    "ANOMES": "2020-05",
    "QTDE_VISIT": 2870
}, {
    "GRUPOMERCADO": "AQUICULTURA",
    "ANOMES": "2020-07",
    "QTDE_VISIT": 20
}, {
    "GRUPOMERCADO": "AVICULTURA",
    "ANOMES": "2020-07",
    "QTDE_VISIT": 70
}, {
    "GRUPOMERCADO": "ANIMAIS DE COMPANHIA",
    "ANOMES": "2020-08",
    "QTDE_VISIT": 2718
}, {
    "GRUPOMERCADO": "ANIMAIS DE COMPANHIA",
    "ANOMES": "2020-10",
    "QTDE_VISIT": 1949
}, {
    "GRUPOMERCADO": "SUINOCULTURA",
    "ANOMES": "2020-10",
    "QTDE_VISIT": 109
}, {
    "GRUPOMERCADO": "SUINOCULTURA",
    "ANOMES": "2021-01",
    "QTDE_VISIT": 69
}, {
    "GRUPOMERCADO": "AVICULTURA",
    "ANOMES": "2021-05",
    "QTDE_VISIT": 95
}, {
    "GRUPOMERCADO": "PECUÁRIA",
    "ANOMES": "2021-06",
    "QTDE_VISIT": 3473
}, {
    "GRUPOMERCADO": "AVICULTURA",
    "ANOMES": "2020-02",
    "QTDE_VISIT": 79
}, {
    "GRUPOMERCADO": "AVICULTURA",
    "ANOMES": "2020-03",
    "QTDE_VISIT": 50
}, {
    "GRUPOMERCADO": "ANIMAIS DE COMPANHIA",
    "ANOMES": "2020-04",
    "QTDE_VISIT": 1781
}, {
    "GRUPOMERCADO": "PECUÁRIA",
    "ANOMES": "2020-04",
    "QTDE_VISIT": 3284
}, {
    "GRUPOMERCADO": "ANIMAIS DE COMPANHIA",
    "ANOMES": "2020-07",
    "QTDE_VISIT": 2128
}, {
    "GRUPOMERCADO": "PECUÁRIA",
    "ANOMES": "2020-07",
    "QTDE_VISIT": 3920
}, {
    "GRUPOMERCADO": "SUINOCULTURA",
    "ANOMES": "2020-11",
    "QTDE_VISIT": 81
}, {
    "GRUPOMERCADO": "SUINOCULTURA",
    "ANOMES": "2021-03",
    "QTDE_VISIT": 75
}, {
    "GRUPOMERCADO": "ANIMAIS DE COMPANHIA",
    "ANOMES": "2021-04",
    "QTDE_VISIT": 1709
}, {
    "GRUPOMERCADO": "AVICULTURA",
    "ANOMES": "2021-04",
    "QTDE_VISIT": 100
}, {
    "GRUPOMERCADO": "PECUÁRIA",
    "ANOMES": "2021-04",
    "QTDE_VISIT": 3240
}, {
    "GRUPOMERCADO": "ANIMAIS DE COMPANHIA",
    "ANOMES": "2021-05",
    "QTDE_VISIT": 889
}, {
    "GRUPOMERCADO": "PECUÁRIA",
    "ANOMES": "2021-05",
    "QTDE_VISIT": 2146
}, {
    "GRUPOMERCADO": "AQUICULTURA",
    "ANOMES": "2021-06",
    "QTDE_VISIT": 15
}, {
    "GRUPOMERCADO": "AVICULTURA",
    "ANOMES": "2021-06",
    "QTDE_VISIT": 87
}, {
    "GRUPOMERCADO": "AVICULTURA",
    "ANOMES": "2020-05",
    "QTDE_VISIT": 131
}, {
    "GRUPOMERCADO": "AVICULTURA",
    "ANOMES": "2020-08",
    "QTDE_VISIT": 85
}, {
    "GRUPOMERCADO": "ANIMAIS DE COMPANHIA",
    "ANOMES": "2020-09",
    "QTDE_VISIT": 2331
}, {
    "GRUPOMERCADO": "PECUÁRIA",
    "ANOMES": "2020-09",
    "QTDE_VISIT": 3855
}, {
    "GRUPOMERCADO": "AVICULTURA",
    "ANOMES": "2020-10",
    "QTDE_VISIT": 74
}, {
    "GRUPOMERCADO": "ANIMAIS DE COMPANHIA",
    "ANOMES": "2020-11",
    "QTDE_VISIT": 1915
}, {
    "GRUPOMERCADO": "AQUICULTURA",
    "ANOMES": "2020-11",
    "QTDE_VISIT": 2
}, {
    "GRUPOMERCADO": "AVICULTURA",
    "ANOMES": "2020-11",
    "QTDE_VISIT": 84
}, {
    "GRUPOMERCADO": "PECUÁRIA",
    "ANOMES": "2020-11",
    "QTDE_VISIT": 3722
}, {
    "GRUPOMERCADO": "ANIMAIS DE COMPANHIA",
    "ANOMES": "2020-12",
    "QTDE_VISIT": 1360
}, {
    "GRUPOMERCADO": "AQUICULTURA",
    "ANOMES": "2020-12",
    "QTDE_VISIT": 3
}, {
    "GRUPOMERCADO": "PECUÁRIA",
    "ANOMES": "2020-12",
    "QTDE_VISIT": 1778
}, {
    "GRUPOMERCADO": "ANIMAIS DE COMPANHIA",
    "ANOMES": "2021-02",
    "QTDE_VISIT": 1802
}, {
    "GRUPOMERCADO": "AVICULTURA",
    "ANOMES": "2021-02",
    "QTDE_VISIT": 83
}, {
    "GRUPOMERCADO": "ANIMAIS DE COMPANHIA",
    "ANOMES": "2021-03",
    "QTDE_VISIT": 1953
}, {
    "GRUPOMERCADO": "AQUICULTURA",
    "ANOMES": "2021-03",
    "QTDE_VISIT": 15
}, {
    "GRUPOMERCADO": "PECUÁRIA",
    "ANOMES": "2021-03",
    "QTDE_VISIT": 3473
}, {
    "GRUPOMERCADO": "SUINOCULTURA",
    "ANOMES": "2021-06",
    "QTDE_VISIT": 75
}]